helix_jupyter_thing/__about__.py
helix_jupyter_thing/__init__.py
helix_jupyter_thing/entrypoint.py
helix_jupyter_thing/kernel.py
helix_jupyter_thing/state.py
helix_jupyter_thing/cli/__init__.py
helix_jupyter_thing/cli/exec.py
helix_jupyter_thing/cli/kernel.py
helix_jupyter_thing-0.1.1.dist-info/METADATA
helix_jupyter_thing-0.1.1.dist-info/WHEEL
helix_jupyter_thing-0.1.1.dist-info/entry_points.txt
helix_jupyter_thing-0.1.1.dist-info/licenses/LICENSE.txt
helix_jupyter_thing-0.1.1.dist-info/RECORD
